Metadata-Version: 2.1
Name: python-rektor-monitor
Version: 0.1.1
Summary: 
License: MIT
Author: samanthagburek
Author-email: sgg2056@nyu.edu
Requires-Python: >=3.12,<4.0
Classifier: License :: OSI Approved :: MIT License
Classifier: Programming Language :: Python :: 3
Classifier: Programming Language :: Python :: 3.12
Classifier: Programming Language :: Python :: 3.13
Requires-Dist: annotated-types (==0.7.0)
Requires-Dist: anyio (==4.6.2.post1)
Requires-Dist: argcomplete (==3.5.1)
Requires-Dist: arrow (==1.3.0)
Requires-Dist: astor (==0.8.1)
Requires-Dist: astroid (==3.3.5)
Requires-Dist: attrs (==24.2.0)
Requires-Dist: autodocstrings (==0.1.3)
Requires-Dist: bandit (==1.7.10)
Requires-Dist: black (==24.10.0)
Requires-Dist: boolean-py (==4.0)
Requires-Dist: certifi (==2024.8.30)
Requires-Dist: cffi (==1.17.1)
Requires-Dist: cfgv (==3.4.0)
Requires-Dist: chardet (==5.2.0)
Requires-Dist: charset-normalizer (==3.4.0)
Requires-Dist: click (==8.1.7)
Requires-Dist: coverage (==7.6.9)
Requires-Dist: cryptography (==44.0.0)
Requires-Dist: cyclonedx-bom (==5.1.1)
Requires-Dist: cyclonedx-python-lib (==8.5.0)
Requires-Dist: defusedxml (==0.7.1)
Requires-Dist: dill (==0.3.9)
Requires-Dist: distlib (==0.3.9)
Requires-Dist: distro (==1.9.0)
Requires-Dist: filelock (==3.16.1)
Requires-Dist: flake8 (==7.1.1)
Requires-Dist: fqdn (==1.5.1)
Requires-Dist: h11 (==0.14.0)
Requires-Dist: httpcore (==1.0.6)
Requires-Dist: httpx (==0.27.2)
Requires-Dist: identify (==2.6.1)
Requires-Dist: idna (==3.10)
Requires-Dist: iniconfig (==2.0.0)
Requires-Dist: isoduration (==20.11.0)
Requires-Dist: isort (==5.13.2)
Requires-Dist: jiter (==0.7.0)
Requires-Dist: jsonpointer (==3.0.0)
Requires-Dist: jsonschema (==4.23.0)
Requires-Dist: jsonschema-specifications (==2024.10.1)
Requires-Dist: license-expression (==30.4.0)
Requires-Dist: lxml (==5.3.0)
Requires-Dist: markdown-it-py (==3.0.0)
Requires-Dist: mccabe (==0.7.0)
Requires-Dist: mdurl (==0.1.2)
Requires-Dist: mocker (==1.1.1)
Requires-Dist: mypy (==1.13.0)
Requires-Dist: mypy-extensions (==1.0.0)
Requires-Dist: nodeenv (==1.9.1)
Requires-Dist: openai (==1.54.3)
Requires-Dist: packageurl-python (==0.16.0)
Requires-Dist: packaging (==24.2)
Requires-Dist: pathspec (==0.12.1)
Requires-Dist: pbr (==6.1.0)
Requires-Dist: pip-requirements-parser (==32.0.1)
Requires-Dist: pipx (==1.7.1)
Requires-Dist: platformdirs (==4.3.6)
Requires-Dist: pluggy (==1.5.0)
Requires-Dist: pre-commit (==4.0.1)
Requires-Dist: py-serializable (==1.1.2)
Requires-Dist: pycodestyle (==2.12.1)
Requires-Dist: pycparser (==2.22)
Requires-Dist: pydantic (==2.9.2)
Requires-Dist: pydantic-core (==2.23.4)
Requires-Dist: pyflakes (==3.2.0)
Requires-Dist: pygments (==2.18.0)
Requires-Dist: pylint (==3.3.1)
Requires-Dist: pyparsing (==3.2.0)
Requires-Dist: pytest (==8.3.4)
Requires-Dist: pytest-cov (==6.0.0)
Requires-Dist: pytest-mock (==3.14.0)
Requires-Dist: python-dateutil (==2.9.0.post0)
Requires-Dist: pyyaml (==6.0.2)
Requires-Dist: referencing (==0.35.1)
Requires-Dist: requests (==2.32.3)
Requires-Dist: rfc3339-validator (==0.1.4)
Requires-Dist: rfc3987 (==1.3.8)
Requires-Dist: rich (==13.9.4)
Requires-Dist: rpds-py (==0.22.3)
Requires-Dist: ruff (==0.7.3)
Requires-Dist: setuptools (==75.6.0)
Requires-Dist: shellingham (==1.5.4)
Requires-Dist: six (==1.16.0)
Requires-Dist: sniffio (==1.3.1)
Requires-Dist: sortedcontainers (==2.4.0)
Requires-Dist: stevedore (==5.3.0)
Requires-Dist: tomlkit (==0.13.2)
Requires-Dist: tqdm (==4.67.0)
Requires-Dist: typer (==0.13.0)
Requires-Dist: types-python-dateutil (==2.9.0.20241003)
Requires-Dist: types-requests (==2.32.0.20241016)
Requires-Dist: typing-extensions (==4.12.2)
Requires-Dist: uri-template (==1.3.0)
Requires-Dist: urllib3 (==2.2.3)
Requires-Dist: userpath (==1.9.2)
Requires-Dist: virtualenv (==20.27.1)
Requires-Dist: webcolors (==24.11.1)
